README.rst
setup.py
pytest_symbols/__init__.py
pytest_symbols/exceptions.py
pytest_symbols/models.py
pytest_symbols/plugin.py
pytest_symbols.egg-info/PKG-INFO
pytest_symbols.egg-info/SOURCES.txt
pytest_symbols.egg-info/dependency_links.txt
pytest_symbols.egg-info/entry_points.txt
pytest_symbols.egg-info/requires.txt
pytest_symbols.egg-info/top_level.txt