Metadata-Version: 1.1
Name: pytest-symbols
Version: 0.1.1
Summary: pytest-symbols is a pytest plugin that adds support for passing test environment symbols into pytest tests.
Home-page: https://github.com/F5Networks/pytest-symbols
Author: F5 Networks
Author-email: qetools@f5.com
License: Apache License, Version 2.0
Keywords: F5,testing
Platform: UNKNOWN
Classifier: Development Status :: 3 - Alpha
Classifier: License :: OSI Approved :: Apache Software License
Classifier: Operating System :: OS Independent
Classifier: Programming Language :: Python
Classifier: Intended Audience :: Developers
Classifier: Topic :: Software Development :: Testing
